LICENSE
rejx/__init__.py
rejx/__main__.py
rejx/cli.py
rejx/exceptions.py
rejx/logger.py
rejx/logo.py
rejx/utils.py
rejx/version.py
rejx-0.2.0.dist-info/LICENSE
rejx-0.2.0.dist-info/METADATA
rejx-0.2.0.dist-info/WHEEL
rejx-0.2.0.dist-info/entry_points.txt
rejx-0.2.0.dist-info/RECORD
