Metadata-Version: 2.1
Name: rejx
Version: 0.2.0
Summary: Rej(spe)X - Deal with .rej file with minimal pain
Home-page: https://github.com/markussagen/rejx
License: MIT
Keywords: git,cookiecutter,cruft,rej
Author: Markus Sagen
Author-email: Markus.John.Sagen@gmail.com
Requires-Python: >=3.8,<4.0
Classifier: License :: OSI Approved :: MIT License
Classifier: Programming Language :: Python :: 3
Classifier: Programming Language :: Python :: 3.8
Classifier: Programming Language :: Python :: 3.9
Classifier: Programming Language :: Python :: 3.10
Classifier: Programming Language :: Python :: 3.11
Classifier: Programming Language :: Python :: 3.12
Requires-Dist: rich (>=12.0.0)
Requires-Dist: typer (>=0.8.0)
Project-URL: Repository, https://github.com/markussagen/rejx
